Metadata-Version: 2.1
Name: rocket_aya_hamdi
Version: 1.0.0
Summary: An awesome package that does something
Home-page: http://pypi.python.org/pypi/rocket/
Author: hamdi aya
Author-email: ay.hamdi@esi-sba.dz
License: LICENSE.txt
License-File: LICENSE.txt
Requires-Dist: rocket_aya_hamdi
